[
  {
    "id": 8,
    "questionId": 4,
    "name": "三等闲",
    "content": "39（不加赖子）",
    "time": "2026-04-26 17:04:14"
  },
  {
    "id": 9,
    "questionId": 4,
    "name": "惜痕",
    "content": "3张",
    "time": "2026-04-26 19:01:20"
  },
  {
    "id": 10,
    "questionId": 4,
    "name": "27张",
    "content": "27张",
    "time": "2026-04-26 19:02:41"
  },
  {
    "id": 11,
    "questionId": 4,
    "name": "本服最异",
    "content": "29（按照52张扑克计算，不含大小王），因为每种花色不连续最多为7张，即4种色28张，再抽一张，一定有一种花色有连续的3个数",
    "time": "2026-04-26 19:10:39"
  },
  {
    "id": 12,
    "questionId": 4,
    "name": "公布答案",
    "content": "37，理由如下\n124578-10-11-13\n这9张*4=36，下一张来牌必定顺子",
    "time": "2026-04-26 19:34:07"
  }
]